searchpods/__init__.py
searchpods-0.1.2.dist-info/WHEEL
searchpods-0.1.2.dist-info/METADATA
searchpods-0.1.2.dist-info/RECORD
