Metadata-Version: 2.1
Name: searchpods
Version: 0.1.2
Summary: Let's find some podcasts!
Home-page: https://github.com/xyclos/podsearch
Author: Jake Johnson
Author-email: jakej587@gmail.com
Requires-Python: >=3.7
Classifier: License :: OSI Approved :: GNU General Public License v3 or later (GPLv3+)
